makru/__init__.py
makru/helpers.py
makru/main.py
makru/makru.py
makru/plug.py
makru/store.py
makru/test_helpers.py
makru/test_makru.py
makru/test_plug.py
makru/test_store.py
makru/yamlh.py
makru-0.1.0b16.dist-info/LICENSE
makru-0.1.0b16.dist-info/METADATA
makru-0.1.0b16.dist-info/WHEEL
makru-0.1.0b16.dist-info/entry_points.txt
makru-0.1.0b16.dist-info/top_level.txt
makru-0.1.0b16.dist-info/RECORD
