Metadata-Version: 2.1
Name: makru
Version: 0.1.0b16
Summary: A simple, readable way to compile your program
Home-page: https://gitlab.com/jinwa/makru
Author: The Makru Contributors
Author-email: UNKNOWN
License: UNKNOWN
Platform: UNKNOWN
Requires-Dist: pluginbase (<2.0.0,>=1.0.0)
Requires-Dist: PyYAML (<6.0.0,>=5.1.1)
Requires-Dist: semver (<3.0.0,>=2.13.0)
